matching/__init__.py
matching/hungarian_match.py
matching/lib.py
matching/recursive_match.py
recursive_matching-1.1.0.dist-info/METADATA
recursive_matching-1.1.0.dist-info/WHEEL
recursive_matching-1.1.0.dist-info/top_level.txt
recursive_matching-1.1.0.dist-info/RECORD
