Metadata-Version: 2.1
Name: recursive-matching
Version: 1.1.0
Summary: Formulating unique assignments recursively.
Home-page: https://github.com/JohnMVSantos/Recursive-Matching
Author: John Santos
Author-email: johnmarisantos@protonmail.com
License: GPL 3.0
Platform: UNKNOWN
Requires-Python: >=3.8.0
Requires-Dist: numpy
